ces_mwaa_utils/__init__.py
ces_mwaa_utils/cli.py
ces_mwaa_utils/lib.py
ces_mwaa_utils-0.1.2.dist-info/entry_points.txt
ces_mwaa_utils-0.1.2.dist-info/WHEEL
ces_mwaa_utils-0.1.2.dist-info/METADATA
ces_mwaa_utils-0.1.2.dist-info/RECORD
