Metadata-Version: 2.1
Name: ces-mwaa-utils
Version: 0.1.2
Summary: Utilities for working for Managed Workflows for Apache Airflow
Author: Manoj Karthick
Author-email: manojkarthick@users.noreply.github.com
Requires-Python: >=3.7,<4.0
Classifier: Programming Language :: Python :: 3
Classifier: Programming Language :: Python :: 3.10
Classifier: Programming Language :: Python :: 3.7
Classifier: Programming Language :: Python :: 3.8
Classifier: Programming Language :: Python :: 3.9
Requires-Dist: PyYAML (==5.4.1)
Requires-Dist: apache-airflow (==2.2.2)
Requires-Dist: apache-airflow-providers-slack (==4.1.0)
Requires-Dist: boto3 (==1.18.65)
Requires-Dist: requests (==2.26.0)
